csv_trans/__init__.py
csv_trans/cli.py
csv_trans/translate.py
csv_trans/utils.py
csv_trans-1.1.4.dist-info/LICENSE
csv_trans-1.1.4.dist-info/METADATA
csv_trans-1.1.4.dist-info/WHEEL
csv_trans-1.1.4.dist-info/entry_points.txt
csv_trans-1.1.4.dist-info/top_level.txt
csv_trans-1.1.4.dist-info/RECORD
