Metadata-Version: 2.1
Name: csv-trans
Version: 1.1.4
Summary: A package for translating csv files across multiple languages
Home-page: https://github.com/ML-Dev-Hub/universal-translator-for-csv-files
Author: Saeed Ahmad
Author-email: saeedahmad.icp@gmail.com
Keywords: python,csv,translate,translator,google,google translator,google translate,translate csv
Classifier: Programming Language :: Python :: 3
Classifier: Intended Audience :: Developers
Classifier: Operating System :: OS Independent
Classifier: License :: OSI Approved :: MIT License
Requires-Python: >=3.6
License-File: LICENSE
Requires-Dist: click
Requires-Dist: beautifulsoup4
Requires-Dist: certifi
Requires-Dist: chardet
Requires-Dist: charset-normalizer
Requires-Dist: colorama
Requires-Dist: deep-translator (==1.10.1)
Requires-Dist: googletrans
Requires-Dist: idna
Requires-Dist: numpy
Requires-Dist: pandas
Requires-Dist: pyarrow
Requires-Dist: python-dateutil
Requires-Dist: pytz
Requires-Dist: requests
Requires-Dist: six
Requires-Dist: soupsieve
Requires-Dist: tqdm
Requires-Dist: urllib3
